qctrlclient/__init__.py
qctrlclient/auth/__init__.py
qctrlclient/auth/api_key.py
qctrlclient/auth/base.py
qctrlclient/auth/cli.py
qctrlclient/auth/constants.py
qctrlclient/auth/helpers.py
qctrlclient/auth/keycloak.py
qctrlclient/auth/mixins.py
qctrlclient/auth/oidc.py
qctrlclient/auth/password.py
qctrlclient/auth/redirect_listener.py
qctrlclient/auth/service_account.py
qctrlclient/auth/token_exchange.py
qctrlclient/client.py
qctrlclient/defaults.py
qctrlclient/exceptions.py
qctrlclient/globals.py
qctrlclient/py.typed
qctrlclient/pytest_plugin.py
qctrl_client-16.0.3.dist-info/LICENSE
qctrl_client-16.0.3.dist-info/METADATA
qctrl_client-16.0.3.dist-info/WHEEL
qctrl_client-16.0.3.dist-info/RECORD
